rahr/__init__.py
rahr/__main__.py
rahr/rahr.py
rahr-2.0.0.dist-info/METADATA
rahr-2.0.0.dist-info/WHEEL
rahr-2.0.0.dist-info/entry_points.txt
rahr-2.0.0.dist-info/top_level.txt
rahr-2.0.0.dist-info/RECORD
