Metadata-Version: 2.1
Name: rahr
Version: 2.0.0
Summary: A python program to search for torrents via Jackett and provide links to stdout
Home-page: https://github.com/blha303/rahr
Author: Alyssa Smith
Author-email: alyssa.dev.smith+rahr@gmail.com
License: MIT
Platform: UNKNOWN
Classifier: Development Status :: 4 - Beta
Classifier: License :: OSI Approved :: MIT License
Classifier: Programming Language :: Python :: 3.4
Classifier: Programming Language :: Python :: 3
Classifier: Intended Audience :: End Users/Desktop
Classifier: Intended Audience :: System Administrators
Classifier: Topic :: Multimedia :: Sound/Audio
Requires-Dist: requests
